{
    "lineas": {
        "1": {
            "idFactura": 1,
            "cantidad": 15,
            "precioVenta": 495,
            "idPase": 0,
            "activo": false
        },
        "2": {
            "idFactura": 2,
            "cantidad": 1,
            "precioVenta": 33,
            "idPase": 0,
            "activo": false
        },
        "3": {
            "idFactura": 0,
            "cantidad": 1,
            "precioVenta": 33,
            "idPase": 0,
            "activo": false
        }
    },
    "lastId": 3
}